{
    "countries": [
        {
            "id": "PL1",
            "code": "PL",
            "name": "Poland",
            "cities": [
                {
                    "id": "C1",
                    "name": "Warsaw"
                }
            ]
        },
        {
            "id": "DE1",
            "code": "DE",
            "name": "Germany",
            "cities": [
                {
                    "id": "C2",
                    "name": "Berlin"
                }
            ]
        }
    ]
}